ChatExchange-0.0.4.dist-info/METADATA
ChatExchange-0.0.4.dist-info/RECORD
ChatExchange-0.0.4.dist-info/WHEEL
ChatExchange-0.0.4.dist-info/top_level.txt
chatexchange/__init__.py
chatexchange/_utils.py
chatexchange/browser.py
chatexchange/client.py
chatexchange/events.py
chatexchange/messages.py
chatexchange/rooms.py
chatexchange/users.py
